{
    "name": "Yellow Rose, The. vol 18, no. 9. (2002)",
    "machine_name": "yellow_rose_the_vol_18_no_9_2002",
    "type": "journal_book",
    "volume": null,
    "number": null,
    "year": "2002",
    "additional_info": null,
    "publish_date": null,
    "pulling_date": null,
    "description": null,
    "archival_data": {
        "id": "2117400",
        "legacy_id": "35949",
        "author": "oitadmin",
        "created": "1473951107"
    },
    "citation_reference_items": [
        {
            "name": "Yellow Rose, The. vol 18, no. 9. (2002) p cover",
            "machine_name": "yellow_rose_the_vol_18_no_9_2002_p_cover",
            "type": "citation_reference",
            "plant": {
                "machine_name": "rosa_cultivars_louise_odier",
                "type": "variety",
                "archival_data": [
                    "1491131"
                ]
            },
            "volume": null,
            "page": "p cover",
            "year": "2002",
            "notes": null,
            "parts_shown": {
                "Flower": true,
                "Seed": false,
                "Fruit": false,
                "Bark": false,
                "Root": false,
                "Habit": false,
                "Leaf": false,
                "Twig": false,
                "Unclear": false
            },
            "citation_type": {
                "Art": false,
                "Photo": false
            },
            "archival_data": {
                "id": "1888506",
                "legacy_id": "230190",
                "AD": false,
                "fpi_pub_issue": null,
                "pullingdat": "7",
                "active": true,
                "author": "oitadmin",
                "created": "1483180383"
            }
        }
    ]
}
